{
  "$schema": "https://raw.githubusercontent.com/spdx/spdx-spec/v2.2.1/schemas/spdx-schema.json",
  "spdxVersion": "SPDX-2.2",
  "dataLicense": "CC0-1.0",
  "SPDXID": "SPDXRef-DOCUMENT",
  "documentNamespace": "https://spdx.org/spdxdocs/fltk-x64-linux-1.3.9-19dbc24b-91de-47d7-be1e-cde57ad19892",
  "name": "fltk:x64-linux@1.3.9 3a9d31c0ab7ffb10b862fa8b32bd78e8c9fb4fb13573ce92519bd887e0d4af82",
  "creationInfo": {
    "creators": [
      "Tool: vcpkg-2024-06-10-02590c430e4ed9215d27870138c2e579cc338772"
    ],
    "created": "2024-06-21T15:55:08Z"
  },
  "relationships": [
    {
      "spdxElementId": "SPDXRef-port",
      "relationshipType": "GENERATES",
      "relatedSpdxElement": "SPDXRef-binary"
    },
    {
      "spdxElementId": "SPDXRef-port",
      "relationshipType": "CONTAINS",
      "relatedSpdxElement": "SPDXRef-file-0"
    },
    {
      "spdxElementId": "SPDXRef-port",
      "relationshipType": "CONTAINS",
      "relatedSpdxElement": "SPDXRef-file-1"
    },
    {
      "spdxElementId": "SPDXRef-port",
      "relationshipType": "CONTAINS",
      "relatedSpdxElement": "SPDXRef-file-2"
    },
    {
      "spdxElementId": "SPDXRef-port",
      "relationshipType": "CONTAINS",
      "relatedSpdxElement": "SPDXRef-file-3"
    },
    {
      "spdxElementId": "SPDXRef-port",
      "relationshipType": "CONTAINS",
      "relatedSpdxElement": "SPDXRef-file-4"
    },
    {
      "spdxElementId": "SPDXRef-port",
      "relationshipType": "CONTAINS",
      "relatedSpdxElement": "SPDXRef-file-5"
    },
    {
      "spdxElementId": "SPDXRef-port",
      "relationshipType": "CONTAINS",
      "relatedSpdxElement": "SPDXRef-file-6"
    },
    {
      "spdxElementId": "SPDXRef-binary",
      "relationshipType": "GENERATED_FROM",
      "relatedSpdxElement": "SPDXRef-port"
    },
    {
      "spdxElementId": "SPDXRef-file-0",
      "relationshipType": "CONTAINED_BY",
      "relatedSpdxElement": "SPDXRef-port"
    },
    {
      "spdxElementId": "SPDXRef-file-1",
      "relationshipType": "CONTAINED_BY",
      "relatedSpdxElement": "SPDXRef-port"
    },
    {
      "spdxElementId": "SPDXRef-file-2",
      "relationshipType": "CONTAINED_BY",
      "relatedSpdxElement": "SPDXRef-port"
    },
    {
      "spdxElementId": "SPDXRef-file-3",
      "relationshipType": "CONTAINED_BY",
      "relatedSpdxElement": "SPDXRef-port"
    },
    {
      "spdxElementId": "SPDXRef-file-4",
      "relationshipType": "CONTAINED_BY",
      "relatedSpdxElement": "SPDXRef-port"
    },
    {
      "spdxElementId": "SPDXRef-file-5",
      "relationshipType": "CONTAINED_BY",
      "relatedSpdxElement": "SPDXRef-port"
    },
    {
      "spdxElementId": "SPDXRef-file-6",
      "relationshipType": "CONTAINED_BY",
      "relatedSpdxElement": "SPDXRef-port"
    }
  ],
  "packages": [
    {
      "name": "fltk",
      "SPDXID": "SPDXRef-port",
      "versionInfo": "1.3.9",
      "downloadLocation": "git+https://github.com/microsoft/vcpkg@171647047716e78f2a85309b6d3b8cb7ca1309c9",
      "homepage": "https://www.fltk.org/",
      "licenseConcluded": "NOASSERTION",
      "licenseDeclared": "NOASSERTION",
      "copyrightText": "NOASSERTION",
      "description": "FLTK (pronounced fulltick) is a cross-platform C++ GUI toolkit for UNIX/Linux (X11), Microsoft Windows, and MacOS X. FLTK provides modern GUI functionality without the bloat and supports 3D graphics via OpenGL and its built-in GLUT emulation.",
      "comment": "This is the port (recipe) consumed by vcpkg."
    },
    {
      "name": "fltk:x64-linux",
      "SPDXID": "SPDXRef-binary",
      "versionInfo": "3a9d31c0ab7ffb10b862fa8b32bd78e8c9fb4fb13573ce92519bd887e0d4af82",
      "downloadLocation": "NONE",
      "licenseConcluded": "NOASSERTION",
      "licenseDeclared": "NOASSERTION",
      "copyrightText": "NOASSERTION",
      "comment": "This is a binary package built by vcpkg."
    },
    {
      "SPDXID": "SPDXRef-resource-1",
      "name": "fltk/fltk",
      "downloadLocation": "git+https://github.com/fltk/fltk@release-1.3.9",
      "licenseConcluded": "NOASSERTION",
      "licenseDeclared": "NOASSERTION",
      "copyrightText": "NOASSERTION",
      "checksums": [
        {
          "algorithm": "SHA512",
          "checksumValue": "2dfeeed9fdc6db62a6620e7c846dbe0bf97dacce3077832e314a35bf16ba6a45803373188a7b3954eada5829385b9914241270b71f12aaf3e9e3df45eb2b1b95"
        }
      ]
    }
  ],
  "files": [
    {
      "fileName": ".//home/aamad/.cache/vcpkg/registries/git-trees/171647047716e78f2a85309b6d3b8cb7ca1309c9/config-path.patch",
      "SPDXID": "SPDXRef-file-0",
      "checksums": [
        {
          "algorithm": "SHA256",
          "checksumValue": "3c8de3510f3e179be6ba52b2684aa877bf7869ff7f75459e03b06f667a9a468f"
        }
      ],
      "licenseConcluded": "NOASSERTION",
      "copyrightText": "NOASSERTION"
    },
    {
      "fileName": ".//home/aamad/.cache/vcpkg/registries/git-trees/171647047716e78f2a85309b6d3b8cb7ca1309c9/portfile.cmake",
      "SPDXID": "SPDXRef-file-1",
      "checksums": [
        {
          "algorithm": "SHA256",
          "checksumValue": "a7bc2b2c7f9bf9aecb25218633b0e2c8f2077353d70970177835327dcfec2536"
        }
      ],
      "licenseConcluded": "NOASSERTION",
      "copyrightText": "NOASSERTION"
    },
    {
      "fileName": ".//home/aamad/.cache/vcpkg/registries/git-trees/171647047716e78f2a85309b6d3b8cb7ca1309c9/math-h-polyfill.patch",
      "SPDXID": "SPDXRef-file-2",
      "checksums": [
        {
          "algorithm": "SHA256",
          "checksumValue": "c629f2385562df307e77e22f56d074950b97605f941829ab69e0296696ecb85d"
        }
      ],
      "licenseConcluded": "NOASSERTION",
      "copyrightText": "NOASSERTION"
    },
    {
      "fileName": ".//home/aamad/.cache/vcpkg/registries/git-trees/171647047716e78f2a85309b6d3b8cb7ca1309c9/fix-system-link.patch",
      "SPDXID": "SPDXRef-file-3",
      "checksums": [
        {
          "algorithm": "SHA256",
          "checksumValue": "6040b70fd147028da009ac332056cc1742f5a3d8b3a1886efb8f6efe0e08b236"
        }
      ],
      "licenseConcluded": "NOASSERTION",
      "copyrightText": "NOASSERTION"
    },
    {
      "fileName": ".//home/aamad/.cache/vcpkg/registries/git-trees/171647047716e78f2a85309b6d3b8cb7ca1309c9/include.patch",
      "SPDXID": "SPDXRef-file-4",
      "checksums": [
        {
          "algorithm": "SHA256",
          "checksumValue": "8e43f5c8bc3572c1b44867d9c3d6b3a661bed2fb40b8e5942fda7772e8848970"
        }
      ],
      "licenseConcluded": "NOASSERTION",
      "copyrightText": "NOASSERTION"
    },
    {
      "fileName": ".//home/aamad/.cache/vcpkg/registries/git-trees/171647047716e78f2a85309b6d3b8cb7ca1309c9/vcpkg.json",
      "SPDXID": "SPDXRef-file-5",
      "checksums": [
        {
          "algorithm": "SHA256",
          "checksumValue": "3293ac7d8f0104134f44f4e399c2eb1d36de61698f59262392534f7f276e2b29"
        }
      ],
      "licenseConcluded": "NOASSERTION",
      "copyrightText": "NOASSERTION"
    },
    {
      "fileName": ".//home/aamad/.cache/vcpkg/registries/git-trees/171647047716e78f2a85309b6d3b8cb7ca1309c9/dependencies.patch",
      "SPDXID": "SPDXRef-file-6",
      "checksums": [
        {
          "algorithm": "SHA256",
          "checksumValue": "493e189a4c7904285ec57f2a6a4bbc73ac6b564084b8d06041aac63bcde24641"
        }
      ],
      "licenseConcluded": "NOASSERTION",
      "copyrightText": "NOASSERTION"
    }
  ]
}
